<?xml version="1.0" encoding="UTF-8"?>
<record xmlns="http://ns.nsdl.org/ncs/ncam_afa"
        xmlns:xsi="http://www.w3.org/2001/XMLSchema-instance"
        xmlns:tdxf="http://teachersdomain.org/functions"
        xsi:schemaLocation="http://ns.nsdl.org/ncs/ncam_afa http://ns.nsdl.org/ncs/ncam_afa/1.00/schemas/record.xsd">
   <general>
      <recordID>idptv11_vid_d4kgen-primary</recordID>
      <recordDate>2011-08-12</recordDate>
      <url>http://www.teachersdomain.org/resource/idptv11.sci.phys.energy.d4kgen/</url>
      <title>Green Energy</title>
      <description> This video segment from IdahoPTV's &lt;em&gt; D4K &lt;/em&gt;describes renewable and non-renewable energy sources and the benefits and drawbacks of each. It provides some ideas about how you can personally conserve energy.     </description>
      <subject>National K -12 Subject::Science::Engineering::Engineering Design::Innovation and Invention</subject>
      <subject>National K -12 Subject::Science::Earth and Space Science::Earth in the Universe::Solar Energy</subject>
      <subject>National K -12 Subject::Science::Earth and Space Science::Earth System, Structure, and Processes::Energy in the Earth System</subject>
      <subject>National K -12 Subject::Science::Earth and Space Science::Earth System, Structure, and Processes::Natural Resources</subject>
      <subject>National K -12 Subject::Science::Earth and Space Science::Water Cycle, Weather, and Climate::Energy Transfer</subject>
      <subject>National K -12 Subject::Science::Physical Science::Energy::Energy Sources</subject>
      <language>en-US</language>
      <mimeType>video/mp4</mimeType>
   </general>
   <educational>
      <educationLevel>Grade 4</educationLevel>
      <educationLevel>Grade 5</educationLevel>
      <educationLevel>Grade 6</educationLevel>
      <audience>Learner</audience>
      <resourceType>Audio/Visual</resourceType>
      <resourceType>Movie/Animation</resourceType>
   </educational>
   <lifecycle>
      <publicationDate>2011-08-12</publicationDate>
      <rights>Download and Share</rights>
      <rights>http://www.teachersdomain.org/oerlicense/2/</rights>
      <accessRights>Free access with registration</accessRights>
      <contributor role="Producer"
                   thumbnail="http://www.teachersdomain.org/assets/image_support/branding/logo/mono/mono_idaho_1.gif">Idaho PTV</contributor>
      <contributor role="Developer"
                   thumbnail="http://www.teachersdomain.org/assets/image_support/branding/logo/mono/mono_idaho.gif">Idaho PTV</contributor>
      <contributor role="Funder"
                   thumbnail="http://www.teachersdomain.org/assets/image_support/branding/logo/mono/mono_iclf.gif">ICFL</contributor>
      <contributor role="Funder"
                   thumbnail="http://www.teachersdomain.org/assets/image_support/branding/logo/mono/mono_bbusa.gif">BTOP</contributor>
   </lifecycle>
   <accessForAll>
      <accessMode>auditory</accessMode>
      <accessMode>textual</accessMode>
      <accessMode>visual</accessMode>
      <adaptationType>captions</adaptationType>
      <adaptationType>transcript</adaptationType>
   </accessForAll>
</record>