<?xml version="1.0" encoding="UTF-8"?>
<record xmlns="http://ns.nsdl.org/ncs/ncam_afa"
        xmlns:xsi="http://www.w3.org/2001/XMLSchema-instance"
        xmlns:tdxf="http://teachersdomain.org/functions"
        xsi:schemaLocation="http://ns.nsdl.org/ncs/ncam_afa http://ns.nsdl.org/ncs/ncam_afa/1.00/schemas/record.xsd">
   <general>
      <recordID>lsps07_sci_phys_matter_stability-lsps07_vid_stability</recordID>
      <recordDate>2007-08-14</recordDate>
      <url>http://www.teachersdomain.org/asset/lsps07_vid_stability/</url>
      <title>Island of Stability</title>
      <description>In this video segment adapted from &lt;em&gt;NOVA scienceNOW&lt;/em&gt;, follow scientists in their quest to understand how stable elements are made and how to create the elusive element 114.</description>
      <subject>National K -12 Subject::Science::Physical Science::Matter::The Atomic Basis of the Properties of Matter</subject>
      <subject>National K -12 Subject::Science::Physical Science::Matter::The Periodic Table</subject>
      <language>en-US</language>
      <mimeType/>
   </general>
   <educational>
      <educationLevel>Grade 9</educationLevel>
      <educationLevel>Grade 10</educationLevel>
      <educationLevel>Grade 11</educationLevel>
      <educationLevel>Grade 12</educationLevel>
      <audience>Learner</audience>
      <resourceType>Audio/Visual</resourceType>
      <resourceType>Movie/Animation</resourceType>
   </educational>
   <lifecycle>
      <publicationDate>2007-08-14</publicationDate>
      <rights>Download and Share</rights>
      <rights>http://www.teachersdomain.org/oerlicense/2/</rights>
      <accessRights>Free access with registration</accessRights>
      <contributor role="Producer"
                   thumbnail="http://www.teachersdomain.org/assets/image_support/branding/logo/mono/mono_wgbh.gif">WGBH Educational Foundation</contributor>
      <contributor role="Developer"
                   thumbnail="http://www.teachersdomain.org/assets/image_support/branding/logo/mono/mono_wgbh.gif">WGBH Educational Foundation</contributor>
      <contributor role="Funder"
                   thumbnail="http://www.teachersdomain.org/assets/image_support/branding/logo/mono/mono_nsf.gif">National Science Foundation</contributor>
   </lifecycle>
   <accessForAll>
      <accessMode>auditory</accessMode>
      <accessMode>visual</accessMode>
      <adaptationType>captions</adaptationType>
   </accessForAll>
</record>